{
  "resources": {
    "body": [
      {
        "type": "style",
        "src": "./build/app.css"
      },
      {
        "type": "script",
        "src": "./build/app.js"
      }
    ]
  },
  "preview": {
    "handlers": [
      {
        "options": ["_default"],
        "execute": "INSTALL_SCOPE.setOptions(INSTALL_OPTIONS)"
      }
    ]
  },
  "options": {
    "properties": {
      "location": {
        "title": "Message Location",
        "description": "Where should the message appear?",
        "order": 0,
        "type": "object",
        "format": "element",
        "default": {
          "selector": "body",
          "method": "prepend"
        }
      },
      "message": {
        "title": "Message",
        "description": "A short example message.",
        "type": "string",
        "format": "richtext",
        "order": 1,
        "default": "<p>Welcome to Cloudflare Apps! This is our example app that utilizes Webpack.</p><p>Download this app every time you want to make a new project with the latest JavaScript and CSS features.</p>"
      }
    }
  }
}
